{
  "temp": {
    "buttonText": ["This is a button.", "Este es un botón."],
    "labelText": ["This is a label", "Esto es una etiqueta."],
    "makeSpanish": ["Make Spanish", "Hacer español."],
    "wasPassedInFromStore": [
      "was passed into this test object.",
      " fue pasado a este objeto de prueba."
    ]
  },
  "login": {
    "username": ["Username", "Nombre de usuario"],
    "password": ["Password", "Contraseña"],
    "login": ["Login", "Iniciar sesión"],
    "register": ["Register", "Registro"],
    "failed": [
      "Failed to log in. Please check your username and password.",
      "Error al iniciar sesión. Por favor verifique su nombre de usuario y contraseña."
    ],
    "loggingIn": ["Logging in...", "Iniciar sesión..."],
    "logout": ["Log out", "cerrar sesión"],
    "required": ["Required", "necesario"]
  },
  "createProject": {
    "name": ["Project Name", "Nombre del Proyecto"],
    "languageData": [
      ".lift language data file",
      "archivo de datos de idioma .lift"
    ],
    "browse": ["Browse Computer", "Navegar por la Computadora"],
    "create": ["Create Project", "Crear Proyecto"],
    "fileSelected": ["File selected", "Archivo seleccionado"]
  },
  "goal": {
    "name": {
      "handleDuplicates": ["Handle Duplicates", "Manejar duplicados"],
      "handleFlags": ["Handle Flags", "Banderas de la manija"],
      "grammarCheck": ["Grammar Check", "Chequeo de gramática"]
    }
  }
}
